sparrowEncryptionDecryption/__init__.py
sparrowEncryptionDecryption/encryption_decryption.py
sparrowEncryptionDecryption/function/__init__.py
sparrowEncryptionDecryption/function/config.py
sparrowEncryptionDecryption/function/decryption.py
sparrowEncryptionDecryption/function/encryption.py
sparrowEncryptionDecryption/tools/__init__.py
sparrowEncryptionDecryption/tools/compress.py
sparrowEncryptionDecryption/tools/error.py
sparrowEncryptionDecryption/tools/tools.py
sparrowencryptiondecryption-0.4.1.dist-info/licenses/LICENSE.txt
sparrowencryptiondecryption-0.4.1.dist-info/METADATA
sparrowencryptiondecryption-0.4.1.dist-info/WHEEL
sparrowencryptiondecryption-0.4.1.dist-info/top_level.txt
sparrowencryptiondecryption-0.4.1.dist-info/RECORD
