Metadata-Version: 2.4
Name: sparrowEncryptionDecryption
Version: 0.4.1
Summary: 基于进制转换、随机抽取与压缩算法的浅加密工具
Home-page: https://github.com/yanshi121/sparrowEncryptionDecryption
Author: 39
Author-email: DY39project@outlook.com
Classifier: Programming Language :: Python :: 3
Classifier: License :: OSI Approved :: MIT License
Classifier: Operating System :: Microsoft :: Windows
Classifier: Operating System :: POSIX :: Linux
Requires-Python: >=3.6
License-File: LICENSE.txt
Requires-Dist: lz4
Requires-Dist: brotli
Requires-Dist: python-snappy
Dynamic: author
Dynamic: author-email
Dynamic: classifier
Dynamic: description
Dynamic: description-content-type
Dynamic: home-page
Dynamic: license-file
Dynamic: requires-dist
Dynamic: requires-python
Dynamic: summary
